CHANGELOG.txt
LICENCE.txt
MANIFEST.in
README.txt
setup.py
sunilcal/__init__.py
sunilcal/sun-cal.py
sunilpm692calsi.egg-info/PKG-INFO
sunilpm692calsi.egg-info/SOURCES.txt
sunilpm692calsi.egg-info/dependency_links.txt
sunilpm692calsi.egg-info/top_level.txt