Metadata-Version: 1.1
Name: sunilpm692calsi
Version: 0.0.2.1
Summary: A very basic calculator
Home-page: UNKNOWN
Author: Sunil PM
Author-email: pm.sunil6@gmail.com
License: MIT
Keywords: calculator
Platform: UNKNOWN
Classifier: Development Status :: 5 - Production/Stable
Classifier: Intended Audience :: Education
Classifier: Operating System :: MacOS :: MacOS X
Classifier: Operating System :: Microsoft :: Windows
Classifier: Operating System :: POSIX
Classifier: License :: OSI Approved :: MIT License
Classifier: Programming Language :: Python :: 3
